setup.py
brynq_sdk_salesforce/__init__.py
brynq_sdk_salesforce/salesforce.py
brynq_sdk_salesforce.egg-info/PKG-INFO
brynq_sdk_salesforce.egg-info/SOURCES.txt
brynq_sdk_salesforce.egg-info/dependency_links.txt
brynq_sdk_salesforce.egg-info/not-zip-safe
brynq_sdk_salesforce.egg-info/requires.txt
brynq_sdk_salesforce.egg-info/top_level.txt